mmarch/__init__.py
mmarch/archive.py
mmarch/format.py
mmarch/hash.py
mmarch/path.py
mmarch_pack-1.0.0.data/scripts/mmarch-pack
mmarch_pack-1.0.0.dist-info/METADATA
mmarch_pack-1.0.0.dist-info/WHEEL
mmarch_pack-1.0.0.dist-info/top_level.txt
mmarch_pack-1.0.0.dist-info/RECORD
