Metadata-Version: 2.1
Name: mmarch-pack
Version: 1.0.0
Summary: Archiving utility for mmarch project, mmap-friendly archive
Home-page: https://github.com/whoozle/mmarch
Author: Vladimir Menshakov
Author-email: vladimir.menshakov@gmail.com
License: UNKNOWN
Platform: UNKNOWN
Classifier: Programming Language :: Python :: 3
Classifier: License :: OSI Approved :: MIT License
Classifier: Operating System :: OS Independent
